supervisor_cli/__init__.py
supervisor_cli/main.py
supervisor_cli-0.1.1.dist-info/licenses/LICENSE
supervisor_cli-0.1.1.dist-info/METADATA
supervisor_cli-0.1.1.dist-info/WHEEL
supervisor_cli-0.1.1.dist-info/entry_points.txt
supervisor_cli-0.1.1.dist-info/top_level.txt
supervisor_cli-0.1.1.dist-info/RECORD
