Metadata-Version: 2.4
Name: supervisor-cli
Version: 0.1.1
Summary: Interactive CLI tool to manage Supervisor services
Author-email: Hitesh <hiteshapr111@gmail.com>
License: MIT
Requires-Python: >=3.8
License-File: LICENSE
Dynamic: license-file
